o3json5-0.1.0.dist-info/METADATA
o3json5-0.1.0.dist-info/WHEEL
o3json5-0.1.0.dist-info/licenses/LICENSE
o3json5/__init__.py
o3json5/o3json5.abi3.so
o3json5-0.1.0.dist-info/RECORD
