Metadata-Version: 2.4
Name: o3json5
Version: 0.1.0
Classifier: Programming Language :: Rust
Classifier: Programming Language :: Python :: Implementation :: CPython
Classifier: Programming Language :: Python :: Implementation :: PyPy
Classifier: Programming Language :: Python :: 3.8
Classifier: Programming Language :: Python :: 3.9
Classifier: Programming Language :: Python :: 3.10
Classifier: Programming Language :: Python :: 3.11
Classifier: Programming Language :: Python :: 3.12
Classifier: Development Status :: 4 - Beta
Classifier: Intended Audience :: Developers
Classifier: Topic :: Software Development :: Libraries :: Python Modules
Classifier: Topic :: Text Processing :: Markup
License-File: LICENSE
Summary: A fast JSON5 parser for Python, written in Rust 🦀
Keywords: json,json5,parser,rust,fast
Author-email: RuneBlaze <liubaqiao@gmail.com>
License: MIT
Requires-Python: >=3.8
Project-URL: Homepage, https://github.com/RuneBlaze/o3json5
Project-URL: Documentation, https://github.com/RuneBlaze/o3json5#readme
